aws_lambda_deployment_package/__init__.py
aws_lambda_deployment_package/deployment_package.py
aws_lambda_deployment_package/lambda_build.sh
aws_lambda_deployment_package/lambda_install.sh
aws_lambda_deployment_package/lambda_optimize.sh
aws_lambda_deployment_package/lambda_post_build.sh
aws_lambda_deployment_package/lambda_post_install.sh
aws_lambda_deployment_package/lambda_pre_build.sh
aws_lambda_deployment_package/lambda_pre_install.sh
aws_lambda_deployment_package-1.2.3.dist-info/LICENSE
aws_lambda_deployment_package-1.2.3.dist-info/METADATA
aws_lambda_deployment_package-1.2.3.dist-info/WHEEL
aws_lambda_deployment_package-1.2.3.dist-info/top_level.txt
aws_lambda_deployment_package-1.2.3.dist-info/RECORD
