Metadata-Version: 2.1
Name: aws-lambda-deployment-package
Version: 1.2.3
Summary: AWS package that helps you create lambda deployment packages.
Home-page: https://github.com/idenfy/AwsLambdaDeploymentPackage.git
Author: Laimonas Sutkus
Author-email: laimonas@idenfy.com, laimonas.sutkus@gmail.com
License: GNU GENERAL PUBLIC LICENSE Version 3
Keywords: AWS Lambda Function Deployment Package
Platform: UNKNOWN
Classifier: Programming Language :: Python :: 3.6
Classifier: Programming Language :: Python :: 3.7
Classifier: Programming Language :: Python :: 3.8
Classifier: Operating System :: OS Independent
